<?xml version="1.0" encoding="utf-8"?>
<!DOCTYPE hibernate-mapping PUBLIC "-//Hibernate/Hibernate Mapping DTD 3.0//EN"
"http://hibernate.sourceforge.net/hibernate-mapping-3.0.dtd">
<!-- 
    Mapping file autogenerated by MyEclipse Persistence Tools
-->
<hibernate-mapping>
    <class name="bean.edu.Person" table="medu_person" catalog="medu">
        <id name="id" type="java.lang.Integer">
            <column name="id" />
            <generator class="identity"></generator>
        </id>
        <property name="name" type="java.lang.String">
            <column name="name" length="45" not-null="true" />
        </property>
        <property name="birthday" type="java.util.Date">
            <column name="birthday" length="10" />
        </property>
        <property name="hobby" type="java.lang.String">
            <column name="hobby" length="45" />
        </property>
        <property name="nativplace" type="java.lang.String">
            <column name="nativplace" length="45" />
        </property>
        <property name="sex" type="java.lang.String">
            <column name="sex" length="2" />
        </property>
        <property name="normallycity" type="java.lang.String">
            <column name="normallycity" length="45" />
        </property>
        <property name="phone" type="java.lang.String">
            <column name="phone" length="45" />
        </property>
        <property name="address" type="java.lang.String">
            <column name="address" length="100" />
        </property>
        <set name="MClasses" inverse="true">
            <key>
                <column name="teacher" />
            </key>
            <one-to-many class="bean.edu.MClass" />
        </set>
        <set name="paymentsForPayer" inverse="true">
            <key>
                <column name="payer" not-null="true" />
            </key>
            <one-to-many class="bean.edu.Payment" />
        </set>
        <set name="students" inverse="true">
            <key>
                <column name="person" />
            </key>
            <one-to-many class="bean.edu.Student" />
        </set>
        <set name="paymentsForPayee" inverse="true">
            <key>
                <column name="payee" not-null="true" />
            </key>
            <one-to-many class="bean.edu.Payment" />
        </set>
    </class>
</hibernate-mapping>
